<?xml version="1.0" encoding="UTF-8"?>
<objects serializationModel="Studio.01.10.00">
    <object class="Event" id="{4b1b6aee-8e63-4156-b1f6-730d7bcf4fa3}">
        <property name="name">
            <value>FootstepsScared</value>
        </property>
        <property name="outputFormat">
            <value>2</value>
        </property>
        <relationship name="folder">
            <destination>{abd39835-5a96-411b-89e8-f81ffa18fcde}</destination>
        </relationship>
        <relationship name="mixer">
            <destination>{fadc49b0-98ea-4c5a-8243-adc8b99adf45}</destination>
        </relationship>
        <relationship name="masterTrack">
            <destination>{ae1839b7-acec-480d-9e10-6c41a4452fb5}</destination>
        </relationship>
        <relationship name="mixerInput">
            <destination>{2bb4610d-6e24-46f3-b104-c780269ba9fe}</destination>
        </relationship>
        <relationship name="automatableProperties">
            <destination>{3615256a-694e-4581-8f83-6f9d48b265b3}</destination>
        </relationship>
        <relationship name="markerTracks">
            <destination>{9958ef48-1d28-476e-a275-0b6a87bc930f}</destination>
        </relationship>
        <relationship name="groupTracks">
            <destination>{a152cfbf-c6fc-4f7a-a3e0-d9cc2ea73011}</destination>
            <destination>{61c8aab3-3cad-40dd-8785-7b45115fd97e}</destination>
            <destination>{d9172685-bb59-4945-aae5-929b3db9accf}</destination>
        </relationship>
        <relationship name="timeline">
            <destination>{6451b3b9-4be1-49f9-9d7f-ce677379bf8a}</destination>
        </relationship>
        <relationship name="banks">
            <destination>{2019b378-9052-4b3a-badf-26a8b953752a}</destination>
        </relationship>
    </object>
    <object class="EventMixer" id="{fadc49b0-98ea-4c5a-8243-adc8b99adf45}">
        <relationship name="masterBus">
            <destination>{188ef106-4639-480b-a7b2-de7d2056acaa}</destination>
        </relationship>
    </object>
    <object class="MasterTrack" id="{ae1839b7-acec-480d-9e10-6c41a4452fb5}">
        <relationship name="mixerGroup">
            <destination>{188ef106-4639-480b-a7b2-de7d2056acaa}</destination>
        </relationship>
    </object>
    <object class="MixerInput" id="{2bb4610d-6e24-46f3-b104-c780269ba9fe}">
        <relationship name="effectChain">
            <destination>{83bc2bc1-52a7-468e-bd34-cb1f7ea46346}</destination>
        </relationship>
        <relationship name="panner">
            <destination>{1ef58af7-63b9-411d-9639-aaffc70e0450}</destination>
        </relationship>
        <relationship name="output">
            <destination>{b27336c9-c6c9-4d18-811c-4c9e85fa13dc}</destination>
        </relationship>
    </object>
    <object class="EventAutomatableProperties" id="{3615256a-694e-4581-8f83-6f9d48b265b3}"/>
    <object class="MarkerTrack" id="{9958ef48-1d28-476e-a275-0b6a87bc930f}"/>
    <object class="GroupTrack" id="{a152cfbf-c6fc-4f7a-a3e0-d9cc2ea73011}">
        <relationship name="modules">
            <destination>{45412395-8e68-403b-94fe-3516c0ff75ab}</destination>
        </relationship>
        <relationship name="mixerGroup">
            <destination>{82593c34-899d-4ebe-b176-8cf8f4a8ef5b}</destination>
        </relationship>
    </object>
    <object class="GroupTrack" id="{61c8aab3-3cad-40dd-8785-7b45115fd97e}">
        <relationship name="modules">
            <destination>{282d2f72-b1da-4800-9535-0530caf5568a}</destination>
        </relationship>
        <relationship name="mixerGroup">
            <destination>{44b407f7-c43c-42c6-aef9-fae120671837}</destination>
        </relationship>
    </object>
    <object class="GroupTrack" id="{d9172685-bb59-4945-aae5-929b3db9accf}">
        <relationship name="mixerGroup">
            <destination>{f231d8df-4354-4bd6-845d-0b99d3b0bb1b}</destination>
        </relationship>
    </object>
    <object class="Timeline" id="{6451b3b9-4be1-49f9-9d7f-ce677379bf8a}">
        <relationship name="modules">
            <destination>{45412395-8e68-403b-94fe-3516c0ff75ab}</destination>
            <destination>{282d2f72-b1da-4800-9535-0530caf5568a}</destination>
        </relationship>
    </object>
    <object class="EventMixerMaster" id="{188ef106-4639-480b-a7b2-de7d2056acaa}">
        <property name="volume">
            <value>3.5</value>
        </property>
        <relationship name="effectChain">
            <destination>{091494ac-4076-4a60-832f-803d226e867f}</destination>
        </relationship>
        <relationship name="panner">
            <destination>{d325b9fa-826f-4a93-b80b-6dfa12480407}</destination>
        </relationship>
        <relationship name="mixer">
            <destination>{fadc49b0-98ea-4c5a-8243-adc8b99adf45}</destination>
        </relationship>
    </object>
    <object class="MixerBusEffectChain" id="{83bc2bc1-52a7-468e-bd34-cb1f7ea46346}">
        <relationship name="effects">
            <destination>{6e97a886-5097-4cf8-9c68-c55e988f6391}</destination>
        </relationship>
    </object>
    <object class="MixerBusPanner" id="{1ef58af7-63b9-411d-9639-aaffc70e0450}"/>
    <object class="MultiSound" id="{45412395-8e68-403b-94fe-3516c0ff75ab}">
        <property name="isAsync">
            <value>true</value>
        </property>
        <property name="length">
            <value>1.0800000000000001</value>
        </property>
        <property name="volume">
            <value>-12.5</value>
        </property>
        <property name="pitch">
            <value>2.20000005</value>
        </property>
        <property name="looping">
            <value>true</value>
        </property>
        <property name="randomized">
            <value>false</value>
        </property>
        <property name="playlistMode">
            <value>1</value>
        </property>
        <relationship name="modulators">
            <destination>{a459f5d6-bfac-409a-8b56-48158cd51cb3}</destination>
        </relationship>
        <relationship name="sounds">
            <destination>{91759942-25da-4180-9e8d-1c5e0d7b06d6}</destination>
            <destination>{6c2fb627-5b15-4197-91de-b22d12524e47}</destination>
            <destination>{514f9b4b-ae6c-484e-bcac-424701c5e441}</destination>
            <destination>{ec177be0-d520-476c-8c13-0c1d40cf85e2}</destination>
            <destination>{fa45e2a2-0c28-4903-b966-ddcd55222a16}</destination>
            <destination>{6630a391-7aed-41c6-ac1c-f7fca69e1835}</destination>
        </relationship>
    </object>
    <object class="EventMixerGroup" id="{82593c34-899d-4ebe-b176-8cf8f4a8ef5b}">
        <property name="volume">
            <value>3</value>
        </property>
        <property name="name">
            <value>Audio 1</value>
        </property>
        <relationship name="effectChain">
            <destination>{56eaf773-36df-46df-b7a0-6df20f32eaf0}</destination>
        </relationship>
        <relationship name="panner">
            <destination>{8a32d520-85cf-4345-8721-24a1e5c52569}</destination>
        </relationship>
        <relationship name="output">
            <destination>{188ef106-4639-480b-a7b2-de7d2056acaa}</destination>
        </relationship>
    </object>
    <object class="SingleSound" id="{282d2f72-b1da-4800-9535-0530caf5568a}">
        <property name="length">
            <value>1.04</value>
        </property>
        <relationship name="audioFile">
            <destination>{563bd32a-6c02-40df-a446-6829c85a9569}</destination>
        </relationship>
    </object>
    <object class="EventMixerGroup" id="{44b407f7-c43c-42c6-aef9-fae120671837}">
        <property name="volume">
            <value>-6</value>
        </property>
        <property name="name">
            <value>Audio 2</value>
        </property>
        <relationship name="effectChain">
            <destination>{aa392ab6-d6c2-4ccd-bf73-daf204b11059}</destination>
        </relationship>
        <relationship name="panner">
            <destination>{d6c6af16-87b7-476d-886c-26b47f0125a1}</destination>
        </relationship>
        <relationship name="output">
            <destination>{188ef106-4639-480b-a7b2-de7d2056acaa}</destination>
        </relationship>
    </object>
    <object class="EventMixerGroup" id="{f231d8df-4354-4bd6-845d-0b99d3b0bb1b}">
        <property name="name">
            <value>Audio 3</value>
        </property>
        <relationship name="effectChain">
            <destination>{9fbe41a8-0dce-4522-90a5-3afeaee49311}</destination>
        </relationship>
        <relationship name="panner">
            <destination>{3d191c80-25d9-4643-a236-605173d6f0ad}</destination>
        </relationship>
        <relationship name="output">
            <destination>{188ef106-4639-480b-a7b2-de7d2056acaa}</destination>
        </relationship>
    </object>
    <object class="MixerBusEffectChain" id="{091494ac-4076-4a60-832f-803d226e867f}">
        <relationship name="effects">
            <destination>{388ee692-dcad-4658-8d38-387f7f8f7c86}</destination>
        </relationship>
    </object>
    <object class="MixerBusPanner" id="{d325b9fa-826f-4a93-b80b-6dfa12480407}">
        <property name="surroundPanDirection">
            <value>-92.2458954</value>
        </property>
    </object>
    <object class="MixerBusFader" id="{6e97a886-5097-4cf8-9c68-c55e988f6391}"/>
    <object class="RandomizerModulator" id="{a459f5d6-bfac-409a-8b56-48158cd51cb3}">
        <property name="nameOfPropertyBeingModulated">
            <value>volume</value>
        </property>
    </object>
    <object class="SingleSound" id="{91759942-25da-4180-9e8d-1c5e0d7b06d6}">
        <relationship name="audioFile">
            <destination>{67330a03-9641-41fc-8694-e7f6e058b958}</destination>
        </relationship>
    </object>
    <object class="SingleSound" id="{6c2fb627-5b15-4197-91de-b22d12524e47}">
        <relationship name="audioFile">
            <destination>{f4d7d87b-48a0-4752-b469-6394677b59a3}</destination>
        </relationship>
    </object>
    <object class="SingleSound" id="{514f9b4b-ae6c-484e-bcac-424701c5e441}">
        <relationship name="audioFile">
            <destination>{9e73d9b4-6a7f-4139-808d-3e0ab06961bf}</destination>
        </relationship>
    </object>
    <object class="SingleSound" id="{ec177be0-d520-476c-8c13-0c1d40cf85e2}">
        <relationship name="audioFile">
            <destination>{34eb7c80-393e-4f2c-bfe2-512db8a38836}</destination>
        </relationship>
    </object>
    <object class="SingleSound" id="{fa45e2a2-0c28-4903-b966-ddcd55222a16}">
        <relationship name="audioFile">
            <destination>{58e13dde-a4d1-4f6f-9a6e-7a9b42c28edd}</destination>
        </relationship>
    </object>
    <object class="SingleSound" id="{6630a391-7aed-41c6-ac1c-f7fca69e1835}">
        <relationship name="audioFile">
            <destination>{44f4fce2-1a83-41f0-b2b8-1f49ca182781}</destination>
        </relationship>
    </object>
    <object class="MixerBusEffectChain" id="{56eaf773-36df-46df-b7a0-6df20f32eaf0}">
        <relationship name="effects">
            <destination>{f785a770-a8c2-4be3-aae1-56ad864e0bed}</destination>
            <destination>{3af8f67c-18ec-416d-b583-71d5181a2942}</destination>
            <destination>{3c721fe4-b546-4397-8f88-d0fe32c3bf3f}</destination>
            <destination>{c7459fba-3d08-4388-9e3a-8c19830faa5c}</destination>
        </relationship>
    </object>
    <object class="MixerBusPanner" id="{8a32d520-85cf-4345-8721-24a1e5c52569}"/>
    <object class="MixerBusEffectChain" id="{aa392ab6-d6c2-4ccd-bf73-daf204b11059}">
        <relationship name="effects">
            <destination>{252cd350-2ec6-41be-90e9-fc71385ca157}</destination>
            <destination>{b1d08e17-bf81-4884-b540-9d85ea680c09}</destination>
            <destination>{0ba5cbd1-6d46-46d9-8a83-3a3a41ff4c32}</destination>
        </relationship>
    </object>
    <object class="MixerBusPanner" id="{d6c6af16-87b7-476d-886c-26b47f0125a1}"/>
    <object class="MixerBusEffectChain" id="{9fbe41a8-0dce-4522-90a5-3afeaee49311}">
        <relationship name="effects">
            <destination>{cc9e6453-8838-496a-bfbf-ae6bd468f7af}</destination>
        </relationship>
    </object>
    <object class="MixerBusPanner" id="{3d191c80-25d9-4643-a236-605173d6f0ad}"/>
    <object class="MixerBusFader" id="{388ee692-dcad-4658-8d38-387f7f8f7c86}"/>
    <object class="MixerBusFader" id="{f785a770-a8c2-4be3-aae1-56ad864e0bed}"/>
    <object class="SpatialiserEffect" id="{3af8f67c-18ec-416d-b583-71d5181a2942}">
        <property name="distanceRolloffType">
            <value>2</value>
        </property>
    </object>
    <object class="ThreeEQEffect" id="{3c721fe4-b546-4397-8f88-d0fe32c3bf3f}">
        <property name="lowGain">
            <value>-17.5</value>
        </property>
        <property name="midGain">
            <value>-13.5</value>
        </property>
        <property name="highGain">
            <value>-14.5</value>
        </property>
        <property name="highCrossover">
            <value>1600</value>
        </property>
        <property name="crossoverSlope">
            <value>0</value>
        </property>
    </object>
    <object class="ThreeEQEffect" id="{c7459fba-3d08-4388-9e3a-8c19830faa5c}">
        <property name="lowGain">
            <value>-48</value>
        </property>
        <property name="midGain">
            <value>-24.5</value>
        </property>
        <property name="highGain">
            <value>-9.5</value>
        </property>
        <property name="lowCrossover">
            <value>1850</value>
        </property>
        <property name="highCrossover">
            <value>2500</value>
        </property>
    </object>
    <object class="TremoloEffect" id="{252cd350-2ec6-41be-90e9-fc71385ca157}"/>
    <object class="MixerBusFader" id="{b1d08e17-bf81-4884-b540-9d85ea680c09}"/>
    <object class="SFXReverbEffect" id="{0ba5cbd1-6d46-46d9-8a83-3a3a41ff4c32}">
        <property name="decayTime">
            <value>300</value>
        </property>
        <property name="HFDecayRatio">
            <value>23</value>
        </property>
        <property name="diffusion">
            <value>58</value>
        </property>
        <property name="lowShelfGain">
            <value>-26.5</value>
        </property>
        <property name="highCut">
            <value>900</value>
        </property>
    </object>
    <object class="MixerBusFader" id="{cc9e6453-8838-496a-bfbf-ae6bd468f7af}"/>
</objects>
